test/__init__.py
test/test_color_funcs.py
test/test_rcfile.py
test/test_vars.py
tks/__init__.py
tks/basic.py
tks/color_funcs.py
tks/color_palette.py
tks/color_slider.py
tks/color_square.py
tks/color_tints_and_shades.py
tks/color_wheel.py
tks/colors.py
tks/css3.txt
tks/dates.py
tks/dialog.py
tks/dnd.py
tks/fs.py
tks/icon.py
tks/matrix.py
tks/passwords.py
tks/rc.py
tks/times.py
tks/tooltip.py
tks/x11.txt
tks/i18n/__init__.py
tks/i18n/en_GB/LC_MESSAGES/tks.mo
tks-0.2.1.dist-info/DESCRIPTION.rst
tks-0.2.1.dist-info/METADATA
tks-0.2.1.dist-info/RECORD
tks-0.2.1.dist-info/WHEEL
tks-0.2.1.dist-info/metadata.json
tks-0.2.1.dist-info/top_level.txt
