Metadata-Version: 2.0
Name: tks
Version: 0.2.1
Summary: A collection of Tk widgets
Home-page: https://github.com/sffjunkie/tks
Author: Simon Kennedy
Author-email: sffjunkie+code@gmail.com
License: Apache-2.0
Platform: UNKNOWN
Requires: PIL
Provides-Extra: idth
Requires-Dist: babel; extra == 'idth'
